gembed/__init__.py
gembed/embed.py
gembed/utils.py
gembed/algorithms/__init__.py
gembed/algorithms/deep_walk.py
gembed/algorithms/embedding_algorithm.py
gembed/algorithms/factory.py
gembed/algorithms/node2vec.py
gembed/algorithms/word2Vec.py
gembed/walks/__init__.py
gembed/walks/baised_walk.py
gembed/walks/factory.py
gembed/walks/random_walk.py
gembed-1.0.2.dist-info/LICENSE
gembed-1.0.2.dist-info/METADATA
gembed-1.0.2.dist-info/WHEEL
gembed-1.0.2.dist-info/top_level.txt
gembed-1.0.2.dist-info/RECORD
