Metadata-Version: 2.1
Name: gembed
Version: 1.0.2
Summary: Graph Embedding Package
Home-page: https://github.com/pranavacharya/graph_embedding
Author: Pranav Acharya
Author-email: apranav.acharya@gmail.com
License: MIT License
Platform: UNKNOWN
License-File: LICENSE
Requires-Dist: gensim (==3.6.0)
Requires-Dist: tqdm
